yoflo/__init__.py
yoflo/cli.py
yoflo/client.py
yoflo/core.py
yoflo/daemon.py
yoflo/model.py
yoflo/recording.py
yoflo/utils.py
yoflo/ptz/__init__.py
yoflo/ptz/hid.py
yoflo/ptz/onvif.py
yoflo/ptz/tracker.py
yoflo-1.4.0.dist-info/licenses/LICENSE.txt
yoflo-1.4.0.dist-info/METADATA
yoflo-1.4.0.dist-info/WHEEL
yoflo-1.4.0.dist-info/entry_points.txt
yoflo-1.4.0.dist-info/top_level.txt
yoflo-1.4.0.dist-info/RECORD
