Metadata-Version: 2.4
Name: yoflo
Version: 1.4.0
Summary: YO-FLO: A proof-of-concept in using advanced vision models as a YOLO alternative.
Home-page: https://github.com/CharlesCNorton/yoflo-cli
Author: Charles Norton
Author-email: CharlesCornellNorton@gmail.com
Classifier: Programming Language :: Python :: 3
Classifier: License :: OSI Approved :: MIT License
Classifier: Operating System :: OS Independent
Requires-Python: >=3.6
License-File: LICENSE.txt
Requires-Dist: packages
Requires-Dist: packaging
Requires-Dist: torch
Requires-Dist: timm
Requires-Dist: transformers>=4.38.0
Requires-Dist: Pillow
Requires-Dist: numpy
Requires-Dist: opencv-python
Requires-Dist: huggingface_hub
Requires-Dist: datasets
Requires-Dist: flash-attn
Requires-Dist: yt_dlp
Requires-Dist: scipy
Provides-Extra: onvif
Requires-Dist: onvif-zeep; extra == "onvif"
Provides-Extra: hid
Requires-Dist: hid; extra == "hid"
Provides-Extra: all
Requires-Dist: onvif-zeep; extra == "all"
Requires-Dist: hid; extra == "all"
Dynamic: author
Dynamic: author-email
Dynamic: classifier
Dynamic: description
Dynamic: description-content-type
Dynamic: home-page
Dynamic: license-file
Dynamic: provides-extra
Dynamic: requires-dist
Dynamic: requires-python
Dynamic: summary
